[{"__symbolic":"module","version":3,"metadata":{"BrokerDispatcherService":{"__symbolic":"class","decorators":[{"__symbolic":"call","expression":{"__symbolic":"reference","module":"@angular/core","name":"Injectable"}}],"members":{"__ctor__":[{"__symbolic":"constructor","parameters":[{"__symbolic":"reference","module":"../outlet/broker.publisher","name":"BrokerPublisher"}]}],"dispatchBrokerAction":[{"__symbolic":"method"}],"dispatchBrokerSelector":[{"__symbolic":"method"}]}}}},{"__symbolic":"module","version":1,"metadata":{"BrokerDispatcherService":{"__symbolic":"class","decorators":[{"__symbolic":"call","expression":{"__symbolic":"reference","module":"@angular/core","name":"Injectable"}}],"members":{"__ctor__":[{"__symbolic":"constructor","parameters":[{"__symbolic":"reference","module":"../outlet/broker.publisher","name":"BrokerPublisher"}]}],"dispatchBrokerAction":[{"__symbolic":"method"}],"dispatchBrokerSelector":[{"__symbolic":"method"}]}}}}]